hydra_plugins/hydra_submitit_launcher/__init__.py
hydra_plugins/hydra_submitit_launcher/config.py
hydra_plugins/hydra_submitit_launcher/submitit_launcher.py
hydra_submitit_launcher-1.2.0.dist-info/METADATA
hydra_submitit_launcher-1.2.0.dist-info/WHEEL
hydra_submitit_launcher-1.2.0.dist-info/top_level.txt
hydra_submitit_launcher-1.2.0.dist-info/RECORD
