Metadata-Version: 2.1
Name: hydra-submitit-launcher
Version: 1.2.0
Summary: Submitit Launcher for Hydra apps
Home-page: https://github.com/facebookincubator/submitit
Author: Jeremy Rapin, Jieru Hu, Omry Yadan
Author-email: jrapin@fb.com, jieru@fb.com, omry@fb.com
License: UNKNOWN
Platform: UNKNOWN
Classifier: License :: OSI Approved :: MIT License
Classifier: Programming Language :: Python :: 3.7
Classifier: Programming Language :: Python :: 3.8
Classifier: Programming Language :: Python :: 3.9
Classifier: Programming Language :: Python :: 3.10
Classifier: Operating System :: MacOS
Classifier: Operating System :: POSIX :: Linux
Classifier: Development Status :: 4 - Beta
